[
  {
    "player_id": "643396",
    "player_name": "Isiah Kiner-Falefa",
    "season": "2025",
    "stats": {
      "age": 30,
      "gamesPlayed": 15,
      "groundOuts": 15,
      "airOuts": 14,
      "runs": 4,
      "doubles": 2,
      "triples": 0,
      "homeRuns": 0,
      "strikeOuts": 4,
      "baseOnBalls": 1,
      "intentionalWalks": 0,
      "hits": 6,
      "hitByPitch": 0,
      "avg": ".162",
      "atBats": 37,
      "obp": ".184",
      "slg": ".216",
      "ops": ".400",
      "caughtStealing": 0,
      "stolenBases": 1,
      "stolenBasePercentage": "1.000",
      "caughtStealingPercentage": ".000",
      "groundIntoDoublePlay": 0,
      "numberOfPitches": 139,
      "plateAppearances": 40,
      "totalBases": 8,
      "rbi": 2,
      "leftOnBase": 25,
      "sacBunts": 2,
      "sacFlies": 0,
      "babip": ".182",
      "groundOutsToAirouts": "1.07",
      "catchersInterference": 0,
      "atBatsPerHomeRun": "-.--"
    }
  },
  {
    "player_id": "702332",
    "player_name": "Caleb Durbin",
    "season": "2025",
    "stats": {
      "age": 25,
      "gamesPlayed": 9,
      "groundOuts": 5,
      "airOuts": 8,
      "runs": 3,
      "doubles": 2,
      "triples": 1,
      "homeRuns": 0,
      "strikeOuts": 8,
      "baseOnBalls": 3,
      "intentionalWalks": 0,
      "hits": 8,
      "hitByPitch": 1,
      "avg": ".276",
      "atBats": 29,
      "obp": ".364",
      "slg": ".414",
      "ops": ".778",
      "caughtStealing": 1,
      "stolenBases": 3,
      "stolenBasePercentage": ".750",
      "caughtStealingPercentage": ".250",
      "groundIntoDoublePlay": 1,
      "numberOfPitches": 114,
      "plateAppearances": 33,
      "totalBases": 12,
      "rbi": 2,
      "leftOnBase": 11,
      "sacBunts": 0,
      "sacFlies": 0,
      "babip": ".381",
      "groundOutsToAirouts": "0.63",
      "catchersInterference": 0,
      "atBatsPerHomeRun": "-.--"
    }
  },
  {
    "player_id": "596115",
    "player_name": "Trevor Story",
    "season": "2025",
    "stats": {
      "age": 32,
      "gamesPlayed": 3,
      "groundOuts": 1,
      "airOuts": 3,
      "runs": 2,
      "doubles": 0,
      "triples": 0,
      "homeRuns": 1,
      "strikeOuts": 4,
      "baseOnBalls": 0,
      "intentionalWalks": 0,
      "hits": 5,
      "hitByPitch": 0,
      "avg": ".385",
      "atBats": 13,
      "obp": ".385",
      "slg": ".615",
      "ops": "1.000",
      "caughtStealing": 0,
      "stolenBases": 1,
      "stolenBasePercentage": "1.000",
      "caughtStealingPercentage": ".000",
      "groundIntoDoublePlay": 0,
      "numberOfPitches": 41,
      "plateAppearances": 13,
      "totalBases": 8,
      "rbi": 3,
      "leftOnBase": 5,
      "sacBunts": 0,
      "sacFlies": 0,
      "babip": ".500",
      "groundOutsToAirouts": "0.33",
      "catchersInterference": 0,
      "atBatsPerHomeRun": "13.00"
    }
  },
  {
    "player_id": "680776",
    "player_name": "Jarren Duran",
    "season": "2025",
    "stats": {
      "age": 28,
      "gamesPlayed": 3,
      "groundOuts": 3,
      "airOuts": 3,
      "runs": 1,
      "doubles": 0,
      "triples": 0,
      "homeRuns": 0,
      "strikeOuts": 4,
      "baseOnBalls": 0,
      "intentionalWalks": 0,
      "hits": 1,
      "hitByPitch": 1,
      "avg": ".091",
      "atBats": 11,
      "obp": ".167",
      "slg": ".091",
      "ops": ".258",
      "caughtStealing": 0,
      "stolenBases": 0,
      "stolenBasePercentage": ".---",
      "caughtStealingPercentage": ".---",
      "groundIntoDoublePlay": 0,
      "numberOfPitches": 42,
      "plateAppearances": 12,
      "totalBases": 1,
      "rbi": 0,
      "leftOnBase": 6,
      "sacBunts": 0,
      "sacFlies": 0,
      "babip": ".143",
      "groundOutsToAirouts": "1.00",
      "catchersInterference": 0,
      "atBatsPerHomeRun": "-.--"
    }
  },
  {
    "player_id": "678882",
    "player_name": "Ceddanne Rafaela",
    "season": "2025",
    "stats": {
      "age": 24,
      "gamesPlayed": 3,
      "groundOuts": 2,
      "airOuts": 4,
      "runs": 2,
      "doubles": 0,
      "triples": 0,
      "homeRuns": 0,
      "strikeOuts": 4,
      "baseOnBalls": 2,
      "intentionalWalks": 0,
      "hits": 0,
      "hitByPitch": 0,
      "avg": ".000",
      "atBats": 10,
      "obp": ".167",
      "slg": ".000",
      "ops": ".167",
      "caughtStealing": 0,
      "stolenBases": 0,
      "stolenBasePercentage": ".---",
      "caughtStealingPercentage": ".---",
      "groundIntoDoublePlay": 0,
      "numberOfPitches": 52,
      "plateAppearances": 12,
      "totalBases": 0,
      "rbi": 0,
      "leftOnBase": 7,
      "sacBunts": 0,
      "sacFlies": 0,
      "babip": ".000",
      "groundOutsToAirouts": "0.50",
      "catchersInterference": 0,
      "atBatsPerHomeRun": "-.--"
    }
  },
  {
    "player_id": "665966",
    "player_name": "Carlos Narváez",
    "season": "2025",
    "stats": {
      "age": 26,
      "gamesPlayed": 3,
      "groundOuts": 2,
      "airOuts": 2,
      "runs": 0,
      "doubles": 0,
      "triples": 0,
      "homeRuns": 0,
      "strikeOuts": 4,
      "baseOnBalls": 3,
      "intentionalWalks": 0,
      "hits": 0,
      "hitByPitch": 0,
      "avg": ".000",
      "atBats": 8,
      "obp": ".273",
      "slg": ".000",
      "ops": ".273",
      "caughtStealing": 0,
      "stolenBases": 0,
      "stolenBasePercentage": ".---",
      "caughtStealingPercentage": ".---",
      "groundIntoDoublePlay": 1,
      "numberOfPitches": 54,
      "plateAppearances": 11,
      "totalBases": 0,
      "rbi": 0,
      "leftOnBase": 3,
      "sacBunts": 0,
      "sacFlies": 0,
      "babip": ".000",
      "groundOutsToAirouts": "1.00",
      "catchersInterference": 0,
      "atBatsPerHomeRun": "-.--"
    }
  },
  {
    "player_id": "663853",
    "player_name": "Romy Gonzalez",
    "season": "2025",
    "stats": {
      "age": 28,
      "gamesPlayed": 3,
      "groundOuts": 2,
      "airOuts": 3,
      "runs": 0,
      "doubles": 0,
      "triples": 0,
      "homeRuns": 0,
      "strikeOuts": 3,
      "baseOnBalls": 0,
      "intentionalWalks": 0,
      "hits": 1,
      "hitByPitch": 0,
      "avg": ".111",
      "atBats": 9,
      "obp": ".111",
      "slg": ".111",
      "ops": ".222",
      "caughtStealing": 0,
      "stolenBases": 0,
      "stolenBasePercentage": ".---",
      "caughtStealingPercentage": ".---",
      "groundIntoDoublePlay": 0,
      "numberOfPitches": 36,
      "plateAppearances": 9,
      "totalBases": 1,
      "rbi": 0,
      "leftOnBase": 2,
      "sacBunts": 0,
      "sacFlies": 0,
      "babip": ".167",
      "groundOutsToAirouts": "0.67",
      "catchersInterference": 0,
      "atBatsPerHomeRun": "-.--"
    }
  },
  {
    "player_id": "686765",
    "player_name": "Nick Sogard",
    "season": "2025",
    "stats": {
      "age": 27,
      "gamesPlayed": 2,
      "groundOuts": 1,
      "airOuts": 3,
      "runs": 1,
      "doubles": 1,
      "triples": 0,
      "homeRuns": 0,
      "strikeOuts": 1,
      "baseOnBalls": 0,
      "intentionalWalks": 0,
      "hits": 2,
      "hitByPitch": 0,
      "avg": ".333",
      "atBats": 6,
      "obp": ".333",
      "slg": ".500",
      "ops": ".833",
      "caughtStealing": 0,
      "stolenBases": 0,
      "stolenBasePercentage": ".---",
      "caughtStealingPercentage": ".---",
      "groundIntoDoublePlay": 0,
      "numberOfPitches": 25,
      "plateAppearances": 7,
      "totalBases": 3,
      "rbi": 0,
      "leftOnBase": 2,
      "sacBunts": 1,
      "sacFlies": 0,
      "babip": ".400",
      "groundOutsToAirouts": "0.33",
      "catchersInterference": 0,
      "atBatsPerHomeRun": "-.--"
    }
  },
  {
    "player_id": "807799",
    "player_name": "Masataka Yoshida",
    "season": "2025",
    "stats": {
      "age": 31,
      "gamesPlayed": 3,
      "groundOuts": 2,
      "airOuts": 0,
      "runs": 0,
      "doubles": 0,
      "triples": 0,
      "homeRuns": 0,
      "strikeOuts": 1,
      "baseOnBalls": 0,
      "intentionalWalks": 0,
      "hits": 4,
      "hitByPitch": 0,
      "avg": ".571",
      "atBats": 7,
      "obp": ".571",
      "slg": ".571",
      "ops": "1.142",
      "caughtStealing": 0,
      "stolenBases": 0,
      "stolenBasePercentage": ".---",
      "caughtStealingPercentage": ".---",
      "groundIntoDoublePlay": 0,
      "numberOfPitches": 24,
      "plateAppearances": 7,
      "totalBases": 4,
      "rbi": 2,
      "leftOnBase": 2,
      "sacBunts": 0,
      "sacFlies": 0,
      "babip": ".667",
      "groundOutsToAirouts": "2.00",
      "catchersInterference": 0,
      "atBatsPerHomeRun": "-.--"
    }
  },
  {
    "player_id": "681987",
    "player_name": "Nate Eaton",
    "season": "2025",
    "stats": {
      "age": 28,
      "gamesPlayed": 2,
      "groundOuts": 2,
      "airOuts": 0,
      "runs": 0,
      "doubles": 1,
      "triples": 0,
      "homeRuns": 0,
      "strikeOuts": 1,
      "baseOnBalls": 1,
      "intentionalWalks": 0,
      "hits": 2,
      "hitByPitch": 0,
      "avg": ".400",
      "atBats": 5,
      "obp": ".500",
      "slg": ".600",
      "ops": "1.100",
      "caughtStealing": 0,
      "stolenBases": 0,
      "stolenBasePercentage": ".---",
      "caughtStealingPercentage": ".---",
      "groundIntoDoublePlay": 1,
      "numberOfPitches": 24,
      "plateAppearances": 6,
      "totalBases": 3,
      "rbi": 0,
      "leftOnBase": 1,
      "sacBunts": 0,
      "sacFlies": 0,
      "babip": ".500",
      "groundOutsToAirouts": "2.00",
      "catchersInterference": 0,
      "atBatsPerHomeRun": "-.--"
    }
  },
  {
    "player_id": "677800",
    "player_name": "Wilyer Abreu",
    "season": "2025",
    "stats": {
      "age": 26,
      "gamesPlayed": 3,
      "groundOuts": 0,
      "airOuts": 2,
      "runs": 0,
      "doubles": 0,
      "triples": 0,
      "homeRuns": 0,
      "strikeOuts": 3,
      "baseOnBalls": 0,
      "intentionalWalks": 0,
      "hits": 0,
      "hitByPitch": 0,
      "avg": ".000",
      "atBats": 5,
      "obp": ".000",
      "slg": ".000",
      "ops": ".000",
      "caughtStealing": 0,
      "stolenBases": 0,
      "stolenBasePercentage": ".---",
      "caughtStealingPercentage": ".---",
      "groundIntoDoublePlay": 0,
      "numberOfPitches": 22,
      "plateAppearances": 5,
      "totalBases": 0,
      "rbi": 0,
      "leftOnBase": 2,
      "sacBunts": 0,
      "sacFlies": 0,
      "babip": ".000",
      "groundOutsToAirouts": "0.00",
      "catchersInterference": 0,
      "atBatsPerHomeRun": "-.--"
    }
  },
  {
    "player_id": "655316",
    "player_name": "Andruw Monasterio",
    "season": "2025",
    "stats": {
      "age": 28,
      "gamesPlayed": 4,
      "groundOuts": 0,
      "airOuts": 0,
      "runs": 0,
      "doubles": 0,
      "triples": 0,
      "homeRuns": 0,
      "strikeOuts": 0,
      "baseOnBalls": 1,
      "intentionalWalks": 0,
      "hits": 0,
      "hitByPitch": 0,
      "avg": ".000",
      "atBats": 0,
      "obp": "1.000",
      "slg": ".000",
      "ops": "1.000",
      "caughtStealing": 0,
      "stolenBases": 0,
      "stolenBasePercentage": ".---",
      "caughtStealingPercentage": ".---",
      "groundIntoDoublePlay": 0,
      "numberOfPitches": 5,
      "plateAppearances": 1,
      "totalBases": 0,
      "rbi": 0,
      "leftOnBase": 0,
      "sacBunts": 0,
      "sacFlies": 0,
      "babip": ".---",
      "groundOutsToAirouts": "-.--",
      "catchersInterference": 0,
      "atBatsPerHomeRun": "-.--"
    }
  }
]